{
  "api_name": "hk_fina_indicator",
  "title": "港股财务指标数据",
  "description": "获取港股上市公司财务指标数据，为避免服务器压力，现阶段每次请求最多返回200条记录，可通过设置日期多次请求获取更多数据。权限：需单独开权限或有15000积分，具体权限信息请参考权限列表提示：当前接口按单只股票获取其历史数据，单次请求最大返回10000行数据，可循环提取",
  "input_params": [
    {
      "name": "ts_code",
      "type": "str",
      "required": "Y",
      "description": "股票代码"
    },
    {
      "name": "period",
      "type": "str",
      "required": "N",
      "description": "报告期(格式：YYYYMMDD）"
    },
    {
      "name": "report_type",
      "type": "str",
      "required": "N",
      "description": "报告期类型（Q1一季报Q2半年报Q3三季报Q4年报）"
    },
    {
      "name": "start_date",
      "type": "str",
      "required": "N",
      "description": "报告期开始日期(格式：YYYYMMDD）"
    },
    {
      "name": "end_date",
      "type": "str",
      "required": "N",
      "description": "报告结束日期(格式：YYYYMMDD）"
    }
  ],
  "output_params": [
    {
      "name": "ts_code",
      "type": "str",
      "required": "Y",
      "description": "股票代码"
    },
    {
      "name": "name",
      "type": "str",
      "required": "Y",
      "description": "股票名称"
    },
    {
      "name": "end_date",
      "type": "str",
      "required": "Y",
      "description": "报告期"
    },
    {
      "name": "ind_type",
      "type": "str",
      "required": "Y",
      "description": "报告类型,Q-按报告期(季度),Y-按年度"
    },
    {
      "name": "report_type",
      "type": "str",
      "required": "Y",
      "description": "报告期类型"
    },
    {
      "name": "std_report_date",
      "type": "str",
      "required": "Y",
      "description": "标准报告期"
    },
    {
      "name": "per_netcash_operate",
      "type": "float",
      "required": "Y",
      "description": "每股经营现金流(元)"
    },
    {
      "name": "per_oi",
      "type": "float",
      "required": "Y",
      "description": "每股营业收入(元)"
    },
    {
      "name": "bps",
      "type": "float",
      "required": "Y",
      "description": "每股净资产(元)"
    },
    {
      "name": "basic_eps",
      "type": "float",
      "required": "Y",
      "description": "基本每股收益(元)"
    },
    {
      "name": "diluted_eps",
      "type": "float",
      "required": "Y",
      "description": "稀释每股收益(元)"
    },
    {
      "name": "operate_income",
      "type": "float",
      "required": "Y",
      "description": "营业总收入(元)"
    },
    {
      "name": "operate_income_yoy",
      "type": "float",
      "required": "Y",
      "description": "营业总收入同比增长(%)"
    },
    {
      "name": "gross_profit",
      "type": "float",
      "required": "Y",
      "description": "毛利润(元)"
    },
    {
      "name": "gross_profit_yoy",
      "type": "float",
      "required": "Y",
      "description": "毛利润同比增长(%)"
    },
    {
      "name": "holder_profit",
      "type": "float",
      "required": "Y",
      "description": "归母净利润(元)"
    },
    {
      "name": "holder_profit_yoy",
      "type": "float",
      "required": "Y",
      "description": "归母净利润同比增长(%)"
    },
    {
      "name": "gross_profit_ratio",
      "type": "float",
      "required": "Y",
      "description": "毛利率(%)"
    },
    {
      "name": "eps_ttm",
      "type": "float",
      "required": "Y",
      "description": "ttm每股收益(元)"
    },
    {
      "name": "operate_income_qoq",
      "type": "float",
      "required": "Y",
      "description": "营业总收入滚动环比增长(%)"
    },
    {
      "name": "net_profit_ratio",
      "type": "float",
      "required": "Y",
      "description": "净利率(%)"
    },
    {
      "name": "roe_avg",
      "type": "float",
      "required": "Y",
      "description": "平均净资产收益率(%)"
    },
    {
      "name": "gross_profit_qoq",
      "type": "float",
      "required": "Y",
      "description": "毛利润滚动环比增长(%)"
    },
    {
      "name": "roa",
      "type": "float",
      "required": "Y",
      "description": "总资产净利率(%)"
    },
    {
      "name": "holder_profit_qoq",
      "type": "float",
      "required": "Y",
      "description": "归母净利润滚动环比增长(%)"
    },
    {
      "name": "roe_yearly",
      "type": "float",
      "required": "Y",
      "description": "年化净资产收益率(%)"
    },
    {
      "name": "roic_yearly",
      "type": "float",
      "required": "Y",
      "description": "年化投资回报率(%)"
    },
    {
      "name": "total_assets",
      "type": "float",
      "required": "Y",
      "description": "资产总额"
    },
    {
      "name": "total_liabilities",
      "type": "float",
      "required": "Y",
      "description": "负债总额"
    },
    {
      "name": "tax_ebt",
      "type": "float",
      "required": "Y",
      "description": "所得税/利润总额(%)"
    },
    {
      "name": "ocf_sales",
      "type": "float",
      "required": "Y",
      "description": "经营现金流/营业收入(%)"
    },
    {
      "name": "total_parent_equity",
      "type": "float",
      "required": "Y",
      "description": "本公司权益持有人应占权益"
    },
    {
      "name": "debt_asset_ratio",
      "type": "float",
      "required": "Y",
      "description": "资产负债率(%)"
    },
    {
      "name": "operate_profit",
      "type": "float",
      "required": "Y",
      "description": "经营盈利"
    },
    {
      "name": "pretax_profit",
      "type": "float",
      "required": "Y",
      "description": "除税前盈利"
    },
    {
      "name": "netcash_operate",
      "type": "float",
      "required": "Y",
      "description": "经营活动所得现金流量净额"
    },
    {
      "name": "netcash_invest",
      "type": "float",
      "required": "Y",
      "description": "投资活动耗用现金流量净额"
    },
    {
      "name": "netcash_finance",
      "type": "float",
      "required": "Y",
      "description": "融资活动耗用现金流量净额"
    },
    {
      "name": "end_cash",
      "type": "float",
      "required": "Y",
      "description": "期末的现金及现金等价物"
    },
    {
      "name": "divi_ratio",
      "type": "float",
      "required": "Y",
      "description": "分红比例"
    },
    {
      "name": "dividend_rate",
      "type": "float",
      "required": "Y",
      "description": "股息率"
    },
    {
      "name": "current_ratio",
      "type": "float",
      "required": "Y",
      "description": "流动比率(倍)"
    },
    {
      "name": "common_acs",
      "type": "float",
      "required": "Y",
      "description": "普通股应计股息"
    },
    {
      "name": "currentdebt_debt",
      "type": "float",
      "required": "Y",
      "description": "流动负债/总负债(%)"
    },
    {
      "name": "issued_common_shares",
      "type": "float",
      "required": "Y",
      "description": "已发行普通股"
    },
    {
      "name": "hk_common_shares",
      "type": "float",
      "required": "Y",
      "description": "港股本"
    },
    {
      "name": "per_shares",
      "type": "float",
      "required": "Y",
      "description": "每手股数"
    },
    {
      "name": "total_market_cap",
      "type": "float",
      "required": "Y",
      "description": "总市值"
    },
    {
      "name": "hksk_market_cap",
      "type": "float",
      "required": "Y",
      "description": "港股市值"
    },
    {
      "name": "pe_ttm",
      "type": "float",
      "required": "Y",
      "description": "滚动市盈率"
    },
    {
      "name": "pb_ttm",
      "type": "float",
      "required": "Y",
      "description": "滚动市净率"
    },
    {
      "name": "report_date_sq",
      "type": "str",
      "required": "Y",
      "description": "季报日期"
    },
    {
      "name": "report_type_sq",
      "type": "str",
      "required": "Y",
      "description": "报告类型"
    },
    {
      "name": "operate_income_sq",
      "type": "float",
      "required": "Y",
      "description": "营业收入"
    },
    {
      "name": "dps_hkd",
      "type": "float",
      "required": "Y",
      "description": "每股股息（港元）"
    },
    {
      "name": "operate_income_qoq_sq",
      "type": "float",
      "required": "Y",
      "description": "营业收入环比"
    },
    {
      "name": "net_profit_ratio_sq",
      "type": "float",
      "required": "Y",
      "description": "净利润率"
    },
    {
      "name": "holder_profit_sq",
      "type": "float",
      "required": "Y",
      "description": "归属于股东净利润"
    },
    {
      "name": "holder_profit_qoq_sq",
      "type": "float",
      "required": "Y",
      "description": "归母净利润环比"
    },
    {
      "name": "roe_avg_sq",
      "type": "float",
      "required": "Y",
      "description": "平均净资产收益率"
    },
    {
      "name": "pe_ttm_sq",
      "type": "float",
      "required": "Y",
      "description": "季报滚动市盈率"
    },
    {
      "name": "pb_ttm_sq",
      "type": "float",
      "required": "Y",
      "description": "季报滚动市净率"
    },
    {
      "name": "roa_sq",
      "type": "float",
      "required": "Y",
      "description": "总资产收益率"
    },
    {
      "name": "start_date",
      "type": "float",
      "required": "Y",
      "description": "会计年度起始日"
    },
    {
      "name": "fiscal_year",
      "type": "float",
      "required": "Y",
      "description": "会计年度截止日"
    },
    {
      "name": "currency",
      "type": "str",
      "required": "Y",
      "description": "币种 港元（hkd）"
    },
    {
      "name": "is_cny_code",
      "type": "float",
      "required": "Y",
      "description": "是否人民币代码"
    },
    {
      "name": "dps_hkd_ly",
      "type": "float",
      "required": "Y",
      "description": "上一年每股股息"
    },
    {
      "name": "org_type",
      "type": "str",
      "required": "Y",
      "description": "企业类型"
    },
    {
      "name": "premium_income",
      "type": "float",
      "required": "Y",
      "description": "保费收入"
    },
    {
      "name": "premium_income_yoy",
      "type": "float",
      "required": "Y",
      "description": "保费收入同比"
    },
    {
      "name": "net_interest_income",
      "type": "float",
      "required": "Y",
      "description": "净利息收入"
    },
    {
      "name": "net_interest_income_yoy",
      "type": "float",
      "required": "Y",
      "description": "净利息收入同比"
    },
    {
      "name": "fee_commission_income",
      "type": "float",
      "required": "Y",
      "description": "手续费及佣金收入"
    },
    {
      "name": "fee_commission_income_yoy",
      "type": "float",
      "required": "Y",
      "description": "手续费及佣金收入同比"
    },
    {
      "name": "accounts_rece_tdays",
      "type": "float",
      "required": "Y",
      "description": "应收账款周转率(次)"
    },
    {
      "name": "inventory_tdays",
      "type": "float",
      "required": "Y",
      "description": "存货周转率(次)"
    },
    {
      "name": "current_assets_tdays",
      "type": "float",
      "required": "Y",
      "description": "流动资产周转率(次)"
    },
    {
      "name": "total_assets_tdays",
      "type": "float",
      "required": "Y",
      "description": "总资产周转率(次)"
    },
    {
      "name": "premium_expense",
      "type": "float",
      "required": "Y",
      "description": "保险赔付支出"
    },
    {
      "name": "loan_deposit",
      "type": "float",
      "required": "Y",
      "description": "贷款/存款"
    },
    {
      "name": "loan_equity",
      "type": "float",
      "required": "Y",
      "description": "贷款/股东权益"
    },
    {
      "name": "loan_assets",
      "type": "float",
      "required": "Y",
      "description": "贷款/总资产"
    },
    {
      "name": "deposit_equity",
      "type": "float",
      "required": "Y",
      "description": "存款/股东权益"
    },
    {
      "name": "deposit_assets",
      "type": "float",
      "required": "Y",
      "description": "存款/总资产"
    },
    {
      "name": "equity_multiplier",
      "type": "float",
      "required": "Y",
      "description": "权益乘数"
    },
    {
      "name": "equity_ratio",
      "type": "float",
      "required": "Y",
      "description": "产权比率"
    }
  ]
}